{ "frames": {
   "0": {
    "frame": { "x": 2, "y": 2, "w": 60, "h": 21 },
    "rotated": false,
    "trimmed": true,
    "spriteSourceSize": { "x": 0, "y": 12, "w": 58, "h": 19 },
    "sourceSize": { "w": 64, "h": 32 },
    "duration": 100
   },
   "1": {
    "frame": { "x": 65, "y": 23, "w": 59, "h": 15 },
    "rotated": false,
    "trimmed": true,
    "spriteSourceSize": { "x": 1, "y": 12, "w": 57, "h": 13 },
    "sourceSize": { "w": 64, "h": 32 },
    "duration": 100
   },
   "2": {
    "frame": { "x": 2, "y": 26, "w": 60, "h": 12 },
    "rotated": false,
    "trimmed": true,
    "spriteSourceSize": { "x": 0, "y": 12, "w": 58, "h": 10 },
    "sourceSize": { "w": 64, "h": 32 },
    "duration": 100
   },
   "3": {
    "frame": { "x": 2, "y": 41, "w": 59, "h": 12 },
    "rotated": false,
    "trimmed": true,
    "spriteSourceSize": { "x": 1, "y": 12, "w": 57, "h": 10 },
    "sourceSize": { "w": 64, "h": 32 },
    "duration": 100
   },
   "4": {
    "frame": { "x": 127, "y": 21, "w": 57, "h": 15 },
    "rotated": false,
    "trimmed": true,
    "spriteSourceSize": { "x": 3, "y": 9, "w": 55, "h": 13 },
    "sourceSize": { "w": 64, "h": 32 },
    "duration": 100
   },
   "5": {
    "frame": { "x": 127, "y": 2, "w": 57, "h": 16 },
    "rotated": false,
    "trimmed": true,
    "spriteSourceSize": { "x": 3, "y": 8, "w": 55, "h": 14 },
    "sourceSize": { "w": 64, "h": 32 },
    "duration": 100
   },
   "6": {
    "frame": { "x": 65, "y": 2, "w": 59, "h": 18 },
    "rotated": false,
    "trimmed": true,
    "spriteSourceSize": { "x": 1, "y": 6, "w": 57, "h": 16 },
    "sourceSize": { "w": 64, "h": 32 },
    "duration": 100
   },
   "7": {
    "frame": { "x": 65, "y": 2, "w": 59, "h": 18 },
    "rotated": false,
    "trimmed": true,
    "spriteSourceSize": { "x": 1, "y": 6, "w": 57, "h": 16 },
    "sourceSize": { "w": 64, "h": 32 },
    "duration": 100
   },
   "8": {
    "frame": { "x": 127, "y": 2, "w": 57, "h": 16 },
    "rotated": false,
    "trimmed": true,
    "spriteSourceSize": { "x": 3, "y": 8, "w": 55, "h": 14 },
    "sourceSize": { "w": 64, "h": 32 },
    "duration": 100
   },
   "9": {
    "frame": { "x": 127, "y": 21, "w": 57, "h": 15 },
    "rotated": false,
    "trimmed": true,
    "spriteSourceSize": { "x": 3, "y": 9, "w": 55, "h": 13 },
    "sourceSize": { "w": 64, "h": 32 },
    "duration": 100
   },
   "10": {
    "frame": { "x": 2, "y": 41, "w": 59, "h": 12 },
    "rotated": false,
    "trimmed": true,
    "spriteSourceSize": { "x": 1, "y": 12, "w": 57, "h": 10 },
    "sourceSize": { "w": 64, "h": 32 },
    "duration": 100
   },
   "11": {
    "frame": { "x": 2, "y": 26, "w": 60, "h": 12 },
    "rotated": false,
    "trimmed": true,
    "spriteSourceSize": { "x": 0, "y": 12, "w": 58, "h": 10 },
    "sourceSize": { "w": 64, "h": 32 },
    "duration": 100
   },
   "12": {
    "frame": { "x": 65, "y": 23, "w": 59, "h": 15 },
    "rotated": false,
    "trimmed": true,
    "spriteSourceSize": { "x": 1, "y": 12, "w": 57, "h": 13 },
    "sourceSize": { "w": 64, "h": 32 },
    "duration": 100
   },
   "13": {
    "frame": { "x": 2, "y": 2, "w": 60, "h": 21 },
    "rotated": false,
    "trimmed": true,
    "spriteSourceSize": { "x": 0, "y": 12, "w": 58, "h": 19 },
    "sourceSize": { "w": 64, "h": 32 },
    "duration": 100
   }
 },
 "meta": {
  "app": "https://www.aseprite.org/",
  "version": "1.2.40-x64",
  "image": "manta.png",
  "format": "RGBA8888",
  "size": { "w": 185, "h": 54 },
  "scale": "1",
  "frameTags": [
   { "name": "Swim", "from": 0, "to": 13, "direction": "forward" }
  ],
  "layers": [
   { "name": "Layer 1", "opacity": 255, "blendMode": "normal" }
  ],
  "slices": [
  ]
 }
}
